DarknetGhost/__init__.py
DarknetGhost/courses.py
DarknetGhost/utils.py
darknetghost-0.2.0.dist-info/METADATA
darknetghost-0.2.0.dist-info/WHEEL
darknetghost-0.2.0.dist-info/top_level.txt
darknetghost-0.2.0.dist-info/RECORD
